{
    "urls": {
        "https://amsterdam.raadsinformatie.nl/document/7880446/1/09012f9782a30a08": {
            "checks": {
                "status": 0,
                "200": "2023-08-11 02:25:14.229263",
                "fail": {
                    "from": "2023-08-12 02:23:10.679370",
                    "from-code": 0
                }
            },
            "used": {
                "about.publiccode.net": [
                    "activities/value-and-impact/policy-documents.md",
                    "organization/annual-reports/annual-report-2019-2020.md"
                ]
            }
        },
        "https://amsterdam.raadsinformatie.nl/document/9725293/1/09012f9783374971": {
            "checks": {
                "status": 0,
                "200": "2023-08-11 02:25:15.384750",
                "fail": {
                    "from": "2023-08-12 02:23:41.274251",
                    "from-code": 0
                }
            },
            "used": {
                "about.publiccode.net": [
                    "activities/value-and-impact/policy-documents.md",
                    "organization/annual-reports/annual-report-2019-2020.md"
                ]
            }
        },
        "https://business.gov.nl/regulation/leave-schemes/": {
            "checks": {
                "status": 0,
                "200": "2023-08-09 02:35:59.743826",
                "fail": {
                    "from": "2023-08-10 02:41:45.444531",
                    "from-code": 0,
                    "to": "2023-08-12 02:24:22.058467",
                    "to-code": 0
                }
            },
            "used": {
                "about.publiccode.net": [
                    "activities/staff-information/parental-leave.md"
                ]
            }
        },
        "https://business.gov.nl/regulation/working-conditions-employees/": {
            "checks": {
                "status": 0,
                "200": "2023-08-09 02:36:00.394974",
                "fail": {
                    "from": "2023-08-10 02:42:15.760490",
                    "from-code": 0,
                    "to": "2023-08-12 02:24:52.398671",
                    "to-code": 0
                }
            },
            "used": {
                "about.publiccode.net": [
                    "activities/staff-management/sick-leave.md"
                ]
            }
        },
        "https://business.gov.nl/starting-your-business/choosing-a-business-structure/association/": {
            "checks": {
                "status": 0,
                "200": "2023-08-09 02:36:00.913368",
                "fail": {
                    "from": "2023-08-10 02:42:45.793097",
                    "from-code": 0,
                    "to": "2023-08-12 02:25:22.413731",
                    "to-code": 0
                }
            },
            "used": {
                "about.publiccode.net": [
                    "organization/governance-model.md"
                ]
            }
        }
    },
    "repos": {
        "about.publiccode.net": "failing"
    }
}
