{
    "http://docs.ckan.org/en/latest/contributing/pull-requests.html": {
        "checks": {
            "status": 200,
            "200": "2023-06-16 02:46:12.654505"
        },
        "used": {
            "community-implementation-guide-standard": [
                "criteria/use-continuous-integration.md"
            ]
        }
    },
    "http://list.org/": {
        "checks": {
            "status": 200,
            "200": "2023-06-16 02:46:17.714013"
        },
        "used": {
            "community-implementation-guide-standard": [
                "criteria/make-contributing-easy.md"
            ]
        }
    },
    "https://about.publiccode.net/activities/supporting-codebase-governance/governance-template.html": {
        "checks": {
            "status": 200,
            "200": "2023-06-16 02:46:26.861638"
        },
        "used": {
            "community-implementation-guide-standard": [
                "criteria/welcome-contributors.md"
            ]
        }
    },
    "https://about.publiccode.net/activities/supporting-codebase-governance/technical-roadmap-template.html": {
        "checks": {
            "status": 200,
            "200": "2023-06-16 02:46:26.948799"
        },
        "used": {
            "community-implementation-guide-standard": [
                "criteria/welcome-contributors.md"
            ]
        }
    },
    "https://arstechnica.com/gadgets/2020/02/how-to-choose-an-open-source-license/": {
        "checks": {
            "status": 200,
            "200": "2023-06-16 02:46:27.423504"
        },
        "used": {
            "community-implementation-guide-standard": [
                "criteria/publish-with-an-open-license.md"
            ]
        }
    },
    "https://ash.harvard.edu/publications/best-practices-governance-digital-public-goods": {
        "checks": {
            "status": 200,
            "200": "2023-06-16 02:46:27.686983"
        },
        "used": {
            "community-implementation-guide-standard": [
                "criteria/welcome-contributors.md"
            ]
        }
    },
    "https://bigbluebutton.org/": {
        "checks": {
            "status": 200,
            "200": "2023-06-16 02:46:28.603671"
        },
        "used": {
            "community-implementation-guide-standard": [
                "criteria/make-contributing-easy.md"
            ]
        }
    },
    "https://bitcrowd.dev/a-note-on-commit-messages": {
        "checks": {
            "status": 200,
            "200": "2023-06-16 02:46:28.905818"
        },
        "used": {
            "community-implementation-guide-standard": [
                "criteria/maintain-version-control.md"
            ]
        }
    },
    "https://bpmn.io/": {
        "checks": {
            "status": 200,
            "200": "2023-06-16 02:46:29.456412"
        },
        "used": {
            "community-implementation-guide-standard": [
                "criteria/bundle-policy-and-source-code.md"
            ]
        }
    },
    "https://chat.civictech.se/home": {
        "checks": {
            "status": 200,
            "200": "2023-06-16 02:46:30.079939"
        },
        "used": {
            "community-implementation-guide-standard": [
                "criteria/make-contributing-easy.md"
            ]
        }
    },
    "https://choosealicense.com/": {
        "checks": {
            "status": 200,
            "200": "2023-06-16 02:46:30.749122"
        },
        "used": {
            "community-implementation-guide-standard": [
                "criteria/publish-with-an-open-license.md"
            ]
        }
    },
    "https://ckan.org/": {
        "checks": {
            "status": 200,
            "200": "2023-06-16 02:46:34.623481"
        },
        "used": {
            "community-implementation-guide-standard": [
                "criteria/welcome-contributors.md"
            ]
        }
    },
    "https://ckan.org/showcase": {
        "checks": {
            "status": 200,
            "200": "2023-06-16 02:46:35.571343"
        },
        "used": {
            "community-implementation-guide-standard": [
                "criteria/document-the-code.md"
            ]
        }
    },
    "https://clinic.cyber.harvard.edu/files/2017/03/2017-03_governance-FINAL.pdf": {
        "checks": {
            "status": 200,
            "200": "2023-06-16 02:46:36.082809"
        },
        "used": {
            "community-implementation-guide-standard": [
                "criteria/welcome-contributors.md"
            ]
        }
    },
    "https://code.europa.eu/": {
        "checks": {
            "status": 200,
            "200": "2023-06-16 02:46:36.382615"
        },
        "used": {
            "community-implementation-guide-standard": [
                "criteria/make-the-codebase-findable.md"
            ]
        }
    },
    "https://code.gouv.fr/": {
        "checks": {
            "status": 200,
            "200": "2023-06-16 02:46:37.932446"
        },
        "used": {
            "community-implementation-guide-standard": [
                "criteria/make-the-codebase-findable.md"
            ]
        }
    },
    "https://code.iadb.org/en/about": {
        "checks": {
            "status": 200,
            "200": "2023-06-16 02:46:38.609878"
        },
        "used": {
            "community-implementation-guide-standard": [
                "criteria/make-the-codebase-findable.md"
            ]
        }
    },
    "https://commons.wikimedia.org/wiki/Category:Software_architecture": {
        "checks": {
            "status": 200,
            "200": "2023-06-16 02:46:39.101977"
        },
        "used": {
            "community-implementation-guide-standard": [
                "criteria/document-the-code.md"
            ]
        }
    },
    "https://communityrule.info/": {
        "checks": {
            "status": 200,
            "200": "2023-06-16 02:46:40.012157"
        },
        "used": {
            "community-implementation-guide-standard": [
                "criteria/welcome-contributors.md"
            ]
        }
    },
    "https://componentencatalogus.commonground.nl/producten": {
        "checks": {
            "status": 200,
            "200": "2023-06-16 02:46:40.517098"
        },
        "used": {
            "community-implementation-guide-standard": [
                "criteria/make-the-codebase-findable.md"
            ]
        }
    },
    "https://creativecommons.org/about/videos/creative-commons-kiwi": {
        "checks": {
            "status": 200,
            "200": "2023-06-16 02:46:41.055066"
        },
        "used": {
            "standard.publiccode.net": [
                "criteria/publish-with-an-open-license.md"
            ],
            "standard.publiccode.net-develop": [
                "criteria/publish-with-an-open-license.md"
            ],
            "community-implementation-guide-standard": [
                "criteria/publish-with-an-open-license.md"
            ]
        }
    },
    "https://creativecommons.org/publicdomain/zero/1.0/": {
        "checks": {
            "status": 200,
            "200": "2023-06-16 02:46:42.606350"
        },
        "used": {
            "community-implementation-guide-standard": [
                "LICENSE.md"
            ],
            "bumperscripter": [
                "LICENSE.md",
                "README.md"
            ]
        }
    },
    "https://crowdin.com/": {
        "checks": {
            "status": 200,
            "200": "2023-06-16 02:46:42.694117"
        },
        "used": {
            "community-implementation-guide-standard": [
                "criteria/create-reusable-and-portable-code.md"
            ]
        }
    },
    "https://crowdin.com/translate/decidim": {
        "checks": {
            "status": 200,
            "200": "2023-06-16 02:46:42.826526"
        },
        "used": {
            "community-implementation-guide-standard": [
                "criteria/create-reusable-and-portable-code.md"
            ]
        }
    },
    "https://daniel.haxx.se/blog/2022/06/17/curl-is-reuse-compliant/": {
        "checks": {
            "status": 200,
            "200": "2023-06-16 02:46:42.920372"
        },
        "used": {
            "community-implementation-guide-standard": [
                "criteria/publish-with-an-open-license.md"
            ]
        }
    },
    "https://decidim.org/usedby/": {
        "checks": {
            "status": 200,
            "200": "2023-06-16 02:46:43.409184"
        },
        "used": {
            "community-implementation-guide-standard": [
                "criteria/create-reusable-and-portable-code.md"
            ]
        }
    },
    "https://developer.overheid.nl/repositories": {
        "checks": {
            "status": 200,
            "200": "2023-06-16 02:46:45.379372"
        },
        "used": {
            "community-implementation-guide-standard": [
                "criteria/make-the-codebase-findable.md"
            ]
        }
    },
    "https://developers.italia.it/it/software.html": {
        "checks": {
            "status": 200,
            "200": "2023-06-16 02:46:46.567319"
        },
        "used": {
            "community-implementation-guide-standard": [
                "criteria/make-the-codebase-findable.md"
            ]
        }
    },
    "https://digitalpublicgoods.net/registry/": {
        "checks": {
            "status": 200,
            "200": "2023-06-16 02:46:48.181111"
        },
        "used": {
            "community-implementation-guide-standard": [
                "criteria/make-the-codebase-findable.md"
            ]
        }
    },
    "https://directory.civictech.guide/listing-category/the-tech": {
        "checks": {
            "status": 200,
            "200": "2023-06-16 02:46:52.905057"
        },
        "used": {
            "community-implementation-guide-standard": [
                "criteria/make-the-codebase-findable.md"
            ]
        }
    },
    "https://directory.fsf.org/wiki/Main_Page": {
        "checks": {
            "status": 200,
            "200": "2023-06-16 02:46:53.758679"
        },
        "used": {
            "standard.publiccode.net": [
                "criteria/make-the-codebase-findable.md"
            ],
            "standard.publiccode.net-develop": [
                "criteria/make-the-codebase-findable.md"
            ],
            "community-implementation-guide-standard": [
                "criteria/make-the-codebase-findable.md"
            ]
        }
    },
    "https://docs.gitea.io/en-us/issue-pull-request-templates/": {
        "checks": {
            "status": 200,
            "200": "2023-06-16 02:46:54.416748"
        },
        "used": {
            "community-implementation-guide-standard": [
                "criteria/require-review-of-contributions.md"
            ]
        }
    },
    "https://docs.gitlab.com/ee/user/project/description_templates.html": {
        "checks": {
            "status": 200,
            "200": "2023-06-16 02:46:54.768756"
        },
        "used": {
            "community-implementation-guide-standard": [
                "criteria/require-review-of-contributions.md"
            ]
        }
    },
    "https://docs.gitlab.com/ee/user/project/protected_branches.html": {
        "checks": {
            "status": 200,
            "200": "2023-06-16 02:46:54.912619"
        },
        "used": {
            "community-implementation-guide-standard": [
                "criteria/require-review-of-contributions.md"
            ]
        }
    },
    "https://docusaurus.io/": {
        "checks": {
            "status": 200,
            "200": "2023-06-16 02:46:55.087226"
        },
        "used": {
            "community-implementation-guide-standard": [
                "criteria/document-the-code.md"
            ]
        }
    },
    "https://education.github.com/git-cheat-sheet-education.pdf": {
        "checks": {
            "status": 200,
            "200": "2023-06-16 02:46:57.251403"
        },
        "used": {
            "standard.publiccode.net": [
                "criteria/maintain-version-control.md"
            ],
            "standard.publiccode.net-develop": [
                "criteria/maintain-version-control.md"
            ],
            "community-implementation-guide-standard": [
                "criteria/maintain-version-control.md"
            ]
        }
    },
    "https://ethicalexplorer.org/": {
        "checks": {
            "status": 200,
            "200": "2023-06-16 02:46:58.266184"
        },
        "used": {
            "community-implementation-guide-standard": [
                "criteria/document-codebase-objectives.md"
            ]
        }
    },
    "https://fixmystreet.org/community/": {
        "checks": {
            "status": 200,
            "200": "2023-06-16 02:47:04.701274"
        },
        "used": {
            "community-implementation-guide-standard": [
                "criteria/make-contributing-easy.md"
            ]
        }
    },
    "https://fixmystreet.org/customising/language/": {
        "checks": {
            "status": 200,
            "200": "2023-06-16 02:47:05.156302"
        },
        "used": {
            "community-implementation-guide-standard": [
                "criteria/create-reusable-and-portable-code.md"
            ]
        }
    },
    "https://git.fsfe.org/FSFE/fsfe-website/issues": {
        "checks": {
            "status": 200,
            "200": "2023-06-16 02:47:08.491993"
        },
        "used": {
            "community-implementation-guide-standard": [
                "criteria/make-contributing-easy.md"
            ]
        }
    },
    "https://git.fsfe.org/FSFE/fsfe-website/pulls": {
        "checks": {
            "status": 200,
            "200": "2023-06-16 02:47:09.447110"
        },
        "used": {
            "community-implementation-guide-standard": [
                "criteria/welcome-contributors.md"
            ]
        }
    },
    "https://github.com/Amsterdam/amsterdam.github.io/blob/master/CONTRIBUTING.md": {
        "checks": {
            "status": 200,
            "200": "2023-06-16 02:47:10.346287"
        },
        "used": {
            "community-implementation-guide-standard": [
                "criteria/welcome-contributors.md"
            ]
        }
    },
    "https://github.com/Amsterdam/amsterdam.github.io/blob/master/guides/write-a-readme.md": {
        "checks": {
            "status": 200,
            "200": "2023-06-16 02:47:10.679017"
        },
        "used": {
            "community-implementation-guide-standard": [
                "criteria/document-the-code.md"
            ]
        }
    },
    "https://github.com/HSLdevcom/digitransit-ui/blob/v2/docs/Architecture.md": {
        "checks": {
            "status": 200,
            "200": "2023-06-16 02:47:12.476934"
        },
        "used": {
            "community-implementation-guide-standard": [
                "criteria/document-the-code.md"
            ]
        }
    },
    "https://github.com/OS2Forms/os2forms/tags": {
        "checks": {
            "status": 200,
            "200": "2023-06-16 02:47:13.238479"
        },
        "used": {
            "community-implementation-guide-standard": [
                "criteria/document-codebase-maturity.md"
            ]
        }
    },
    "https://github.com/OpenRefine/OpenRefine/blob/master/GOVERNANCE.md": {
        "checks": {
            "status": 200,
            "200": "2023-06-16 02:47:13.655582"
        },
        "used": {
            "community-implementation-guide-standard": [
                "criteria/welcome-contributors.md"
            ]
        }
    },
    "https://github.com/Seravo/gnitpick": {
        "checks": {
            "status": 200,
            "200": "2023-06-16 02:47:14.969236"
        },
        "used": {
            "community-implementation-guide-standard": [
                "criteria/maintain-version-control.md"
            ]
        }
    },
    "https://github.com/Signalen/backend/blob/master/.github/pull_request_template.md": {
        "checks": {
            "status": 200,
            "200": "2023-06-16 02:47:15.402776"
        },
        "used": {
            "community-implementation-guide-standard": [
                "criteria/require-review-of-contributions.md"
            ]
        }
    },
    "https://github.com/alphagov/notifications-manuals/wiki": {
        "checks": {
            "status": 200,
            "200": "2023-06-16 02:47:16.919457"
        },
        "used": {
            "community-implementation-guide-standard": [
                "criteria/use-plain-english.md"
            ]
        }
    },
    "https://github.com/caramelomartins/awesome-linters": {
        "checks": {
            "status": 200,
            "200": "2023-06-16 02:47:17.789985"
        },
        "used": {
            "community-implementation-guide-standard": [
                "criteria/use-a-coherent-style.md"
            ]
        }
    },
    "https://github.com/git/git/blob/master/Documentation/CodingGuidelines": {
        "checks": {
            "status": 200,
            "200": "2023-06-16 02:47:20.414469"
        },
        "used": {
            "community-implementation-guide-standard": [
                "criteria/use-a-coherent-style.md",
                "criteria/welcome-contributors.md"
            ]
        }
    },
    "https://github.com/licensee/licensee": {
        "checks": {
            "status": 200,
            "200": "2023-06-16 02:47:21.995970"
        },
        "used": {
            "community-implementation-guide-standard": [
                "criteria/publish-with-an-open-license.md"
            ]
        }
    },
    "https://github.com/ministero-salute/it-dgc-verificaC19-android/blob/develop/publiccode.yml": {
        "checks": {
            "status": 200,
            "200": "2023-06-16 02:47:22.821012"
        },
        "used": {
            "community-implementation-guide-standard": [
                "criteria/make-the-codebase-findable.md"
            ]
        }
    },
    "https://github.com/mosip/registration/releases": {
        "checks": {
            "status": 200,
            "200": "2023-06-16 02:47:23.224221"
        },
        "used": {
            "community-implementation-guide-standard": [
                "criteria/maintain-version-control.md"
            ]
        }
    },
    "https://github.com/open-zaak/open-zaak/blob/main/CHANGELOG.rst": {
        "checks": {
            "status": 200,
            "200": "2023-06-16 02:47:24.631423"
        },
        "used": {
            "community-implementation-guide-standard": [
                "criteria/document-codebase-maturity.md"
            ]
        }
    },
    "https://github.com/open-zaak/open-zaak/blob/main/CONTRIBUTING.md": {
        "checks": {
            "status": 200,
            "200": "2023-06-16 02:47:24.932874"
        },
        "used": {
            "standard.publiccode.net": [
                "docs/standard-for-public-code.html"
            ],
            "standard.publiccode.net-develop": [
                "docs/standard-for-public-code.html"
            ],
            "community-implementation-guide-standard": [
                "criteria/use-a-coherent-style.md",
                "criteria/welcome-contributors.md"
            ]
        }
    },
    "https://github.com/open-zaak/open-zaak/blob/main/SECURITY.rst": {
        "checks": {
            "status": 200,
            "200": "2023-06-16 02:47:25.301488"
        },
        "used": {
            "community-implementation-guide-standard": [
                "criteria/make-contributing-easy.md"
            ]
        }
    },
    "https://github.com/open-zaak/open-zaak/blob/main/publiccode.yaml": {
        "checks": {
            "status": 200,
            "200": "2023-06-16 02:47:25.569092"
        },
        "used": {
            "community-implementation-guide-standard": [
                "criteria/make-the-codebase-findable.md"
            ]
        }
    },
    "https://github.com/opengovernment/opengovernment/blob/master/CONTRIBUTING.md": {
        "checks": {
            "status": 200,
            "200": "2023-06-16 02:47:25.859195"
        },
        "used": {
            "community-implementation-guide-standard": [
                "criteria/welcome-contributors.md"
            ]
        }
    },
    "https://github.com/publiccodenet/community-implementation-guide-standard/actions/workflows/pages/pages-build-deployment": {
        "checks": {
            "status": 200,
            "200": "2023-06-16 02:47:27.700969"
        },
        "used": {
            "community-implementation-guide-standard": [
                "README.md"
            ]
        }
    },
    "https://github.com/publiccodenet/community-implementation-guide-standard/actions/workflows/pages/pages-build-deployment/badge.svg": {
        "checks": {
            "status": 200,
            "200": "2023-06-16 02:47:28.319222"
        },
        "used": {
            "community-implementation-guide-standard": [
                "README.md"
            ]
        }
    },
    "https://github.com/publiccodenet/community-implementation-guide-standard/actions/workflows/test.yml": {
        "checks": {
            "status": 200,
            "200": "2023-06-16 02:47:28.578786"
        },
        "used": {
            "community-implementation-guide-standard": [
                "README.md"
            ]
        }
    },
    "https://github.com/publiccodenet/community-implementation-guide-standard/actions/workflows/test.yml/badge.svg": {
        "checks": {
            "status": 200,
            "200": "2023-06-16 02:47:29.273550"
        },
        "used": {
            "community-implementation-guide-standard": [
                "README.md"
            ]
        }
    },
    "https://github.com/publiccodenet/community-implementation-guide-standard/issues": {
        "checks": {
            "status": 200,
            "200": "2023-06-16 02:47:29.551362"
        },
        "used": {
            "community-implementation-guide-standard": [
                "README.md"
            ]
        }
    },
    "https://github.com/publiccodenet/standard/graphs/contributors": {
        "checks": {
            "status": 200,
            "200": "2023-06-16 02:47:37.860143"
        },
        "used": {
            "community-implementation-guide-standard": [
                "criteria/welcome-contributors.md"
            ]
        }
    },
    "https://github.com/publiccodenet/standard/issues": {
        "checks": {
            "status": 200,
            "200": "2023-06-16 02:47:38.091164"
        },
        "used": {
            "standard.publiccode.net": [
                "CONTRIBUTING.md",
                "docs/standard-for-public-code.html"
            ],
            "standard.publiccode.net-develop": [
                "CONTRIBUTING.md",
                "docs/standard-for-public-code.html"
            ],
            "publiccode.net": [
                "standard-for-public-code/index.md"
            ],
            "community-implementation-guide-standard": [
                "criteria/make-contributing-easy.md"
            ]
        }
    },
    "https://github.com/publiccodenet/standard/pulls": {
        "checks": {
            "status": 200,
            "200": "2023-06-16 02:47:38.407899"
        },
        "used": {
            "community-implementation-guide-standard": [
                "criteria/welcome-contributors.md"
            ]
        }
    },
    "https://github.com/publiccodeyml/publiccode.yml/discussions": {
        "checks": {
            "status": 200,
            "200": "2023-06-16 02:47:40.305759"
        },
        "used": {
            "community-implementation-guide-standard": [
                "criteria/make-contributing-easy.md"
            ]
        }
    },
    "https://github.com/verdaccio/verdaccio/blob/master/SECURITY.md": {
        "checks": {
            "status": 200,
            "200": "2023-06-16 02:47:41.461884"
        },
        "used": {
            "community-implementation-guide-standard": [
                "criteria/make-contributing-easy.md"
            ]
        }
    },
    "https://gitlab.opencode.de/explore": {
        "checks": {
            "status": 200,
            "200": "2023-06-16 02:47:41.756359"
        },
        "used": {
            "community-implementation-guide-standard": [
                "criteria/make-the-codebase-findable.md"
            ]
        }
    },
    "https://gitter.im/": {
        "checks": {
            "status": 200,
            "200": "2023-06-16 02:47:43.107725"
        },
        "used": {
            "community-implementation-guide-standard": [
                "criteria/make-contributing-easy.md"
            ]
        }
    },
    "https://governancegame.publiccode.net/": {
        "checks": {
            "status": 200,
            "200": "2023-06-16 02:47:43.943860"
        },
        "used": {
            "community-implementation-guide-standard": [
                "criteria/welcome-contributors.md"
            ]
        }
    },
    "https://hemingwayapp.com/": {
        "checks": {
            "status": 200,
            "200": "2023-06-16 02:47:44.721966"
        },
        "used": {
            "community-implementation-guide-standard": [
                "criteria/use-plain-english.md"
            ]
        }
    },
    "https://jitsi.org/": {
        "checks": {
            "status": 200,
            "200": "2023-06-16 02:47:45.410286"
        },
        "used": {
            "community-implementation-guide-standard": [
                "criteria/make-contributing-easy.md"
            ]
        }
    },
    "https://joinup.ec.europa.eu/collection/eupl/solution/joinup-licensing-assistant/jla-compatibility-checker": {
        "checks": {
            "status": 200,
            "200": "2023-06-16 02:47:45.791197"
        },
        "used": {
            "community-implementation-guide-standard": [
                "criteria/publish-with-an-open-license.md"
            ]
        }
    },
    "https://joinup.ec.europa.eu/collection/eupl/solution/joinup-licensing-assistant/jla-find-and-compare-software-licenses": {
        "checks": {
            "status": 200,
            "200": "2023-06-16 02:47:46.172028"
        },
        "used": {
            "community-implementation-guide-standard": [
                "criteria/publish-with-an-open-license.md"
            ]
        }
    },
    "https://journals.plos.org/ploscompbiol/article?id=10.1371/journal.pcbi.1002598": {
        "checks": {
            "status": 200,
            "200": "2023-06-16 02:47:46.788419"
        },
        "used": {
            "community-implementation-guide-standard": [
                "criteria/publish-with-an-open-license.md"
            ]
        }
    },
    "https://languagetool.org/": {
        "checks": {
            "status": 200,
            "200": "2023-06-16 02:47:47.232237"
        },
        "used": {
            "community-implementation-guide-standard": [
                "criteria/use-plain-english.md"
            ]
        }
    },
    "https://link.springer.com/article/10.1007/s10997-007-9022-9": {
        "checks": {
            "status": 200,
            "200": "2023-06-16 02:47:47.960939"
        },
        "used": {
            "community-implementation-guide-standard": [
                "criteria/welcome-contributors.md"
            ]
        }
    },
    "https://lists.publiccode.net/mailman/postorius/lists/openzaak-discuss.lists.publiccode.net/": {
        "checks": {
            "status": 200,
            "200": "2023-06-16 02:47:48.823263"
        },
        "used": {
            "community-implementation-guide-standard": [
                "criteria/make-contributing-easy.md"
            ]
        }
    },
    "https://lists.publiccode.net/mailman/postorius/lists/standard.lists.publiccode.net/": {
        "checks": {
            "status": 200,
            "200": "2023-06-16 02:47:49.219383"
        },
        "used": {
            "standard.publiccode.net": [
                "CONTRIBUTING.md",
                "docs/standard-for-public-code.html"
            ],
            "standard.publiccode.net-develop": [
                "CONTRIBUTING.md",
                "docs/standard-for-public-code.html"
            ],
            "publiccode.net": [
                "standard-for-public-code/index.md"
            ],
            "community-implementation-guide-standard": [
                "README.md"
            ]
        }
    },
    "https://matrix.org/": {
        "checks": {
            "status": 200,
            "200": "2023-06-16 02:47:49.599820"
        },
        "used": {
            "community-implementation-guide-standard": [
                "criteria/make-contributing-easy.md"
            ]
        }
    },
    "https://mattermost.com/": {
        "checks": {
            "status": 200,
            "200": "2023-06-16 02:47:49.778952"
        },
        "used": {
            "community-implementation-guide-standard": [
                "criteria/make-contributing-easy.md"
            ]
        }
    },
    "https://offentligkod.se/": {
        "checks": {
            "status": 200,
            "200": "2023-06-16 02:47:52.689087"
        },
        "used": {
            "community-implementation-guide-standard": [
                "criteria/make-the-codebase-findable.md"
            ]
        }
    },
    "https://openfisca.org/doc/index.html": {
        "checks": {
            "status": 200,
            "200": "2023-06-16 02:47:54.025004"
        },
        "used": {
            "community-implementation-guide-standard": [
                "criteria/document-the-code.md"
            ]
        }
    },
    "https://openfisca.org/en/packages/": {
        "checks": {
            "status": 200,
            "200": "2023-06-16 02:47:54.392427"
        },
        "used": {
            "community-implementation-guide-standard": [
                "criteria/create-reusable-and-portable-code.md"
            ]
        }
    },
    "https://opensource.com/article/22/10/code-review": {
        "checks": {
            "status": 200,
            "200": "2023-06-16 02:47:56.221236"
        },
        "used": {
            "community-implementation-guide-standard": [
                "criteria/require-review-of-contributions.md"
            ]
        }
    },
    "https://os2.eu/produkt/os2rollekatalog": {
        "checks": {
            "status": 200,
            "200": "2023-06-16 02:47:57.154075"
        },
        "used": {
            "community-implementation-guide-standard": [
                "criteria/welcome-contributors.md"
            ]
        }
    },
    "https://ospo.zone/ggi/": {
        "checks": {
            "status": 200,
            "200": "2023-06-16 02:47:58.824018"
        },
        "used": {
            "community-implementation-guide-standard": [
                "criteria/welcome-contributors.md"
            ]
        }
    },
    "https://phabricator.wikimedia.org/maniphest/": {
        "checks": {
            "status": 200,
            "200": "2023-06-16 02:47:59.902436"
        },
        "used": {
            "community-implementation-guide-standard": [
                "criteria/make-contributing-easy.md"
            ]
        }
    },
    "https://poedit.net/": {
        "checks": {
            "status": 200,
            "200": "2023-06-16 02:48:02.475686"
        },
        "used": {
            "community-implementation-guide-standard": [
                "criteria/create-reusable-and-portable-code.md"
            ]
        }
    },
    "https://publiccode-editor.developers.italia.it/": {
        "checks": {
            "status": 200,
            "200": "2023-06-16 02:48:03.715370"
        },
        "used": {
            "community-implementation-guide-standard": [
                "criteria/make-the-codebase-findable.md"
            ]
        }
    },
    "https://publiccodenet.github.io/publiccodenet-url-check/badges/community-implementation-guide-standard.svg": {
        "checks": {
            "status": 200,
            "200": "2023-06-16 02:48:06.214617"
        },
        "used": {
            "community-implementation-guide-standard": [
                "README.md"
            ]
        }
    },
    "https://publiccodenet.github.io/publiccodenet-url-check/community-implementation-guide-standard-url-check-look.json": {
        "checks": {
            "status": 200,
            "200": "2023-06-16 02:48:06.484058"
        },
        "used": {
            "community-implementation-guide-standard": [
                "README.md"
            ]
        }
    },
    "https://readme.so/": {
        "checks": {
            "status": 200,
            "200": "2023-06-16 02:48:06.999950"
        },
        "used": {
            "community-implementation-guide-standard": [
                "criteria/document-the-code.md"
            ]
        }
    },
    "https://readthedocs.org/": {
        "checks": {
            "status": 200,
            "200": "2023-06-16 02:48:07.138284"
        },
        "used": {
            "community-implementation-guide-standard": [
                "criteria/document-the-code.md"
            ]
        }
    },
    "https://reuse.software/": {
        "checks": {
            "status": 200,
            "200": "2023-06-16 02:48:07.443071"
        },
        "used": {
            "community-implementation-guide-standard": [
                "criteria/publish-with-an-open-license.md"
            ]
        }
    },
    "https://rocket.chat/": {
        "checks": {
            "status": 200,
            "200": "2023-06-16 02:48:08.695819"
        },
        "used": {
            "community-implementation-guide-standard": [
                "criteria/make-contributing-easy.md"
            ]
        }
    },
    "https://rubygems.org": {
        "checks": {
            "status": 200,
            "200": "2023-06-16 02:48:08.930034"
        },
        "used": {
            "standard.publiccode.net": [
                "Gemfile"
            ],
            "standard.publiccode.net-develop": [
                "Gemfile"
            ],
            "publiccode.net": [
                "Gemfile"
            ],
            "community-implementation-guide-standard": [
                "Gemfile"
            ]
        }
    },
    "https://semver.org/": {
        "checks": {
            "status": 200,
            "200": "2023-06-16 02:48:10.277260"
        },
        "used": {
            "standard.publiccode.net": [
                "criteria/document-codebase-maturity.md"
            ],
            "standard.publiccode.net-develop": [
                "criteria/document-codebase-maturity.md"
            ],
            "community-implementation-guide-standard": [
                "criteria/document-codebase-maturity.md"
            ]
        }
    },
    "https://signalen.org": {
        "checks": {
            "status": 200,
            "200": "2023-06-16 02:48:10.544604"
        },
        "used": {
            "publiccode.net": [
                "codebases/index.html",
                "codebases/signalen.html"
            ],
            "community-implementation-guide-standard": [
                "criteria/create-reusable-and-portable-code.md"
            ]
        }
    },
    "https://skills.github.com/": {
        "checks": {
            "status": 200,
            "200": "2023-06-16 02:48:11.393024"
        },
        "used": {
            "standard.publiccode.net": [
                "CONTRIBUTING.md",
                "criteria/maintain-version-control.md"
            ],
            "standard.publiccode.net-develop": [
                "CONTRIBUTING.md",
                "criteria/maintain-version-control.md"
            ],
            "community-implementation-guide-standard": [
                "criteria/maintain-version-control.md"
            ],
            "bumperscripter": [
                "CONTRIBUTING.md"
            ]
        }
    },
    "https://softwarecollaborative.org/": {
        "checks": {
            "status": 200,
            "200": "2023-06-16 02:48:11.594471"
        },
        "used": {
            "community-implementation-guide-standard": [
                "criteria/make-the-codebase-findable.md"
            ]
        }
    },
    "https://solutions.dial.community/": {
        "checks": {
            "status": 200,
            "200": "2023-06-16 02:48:11.949847"
        },
        "used": {
            "community-implementation-guide-standard": [
                "criteria/make-the-codebase-findable.md"
            ]
        }
    },
    "https://spec.openapis.org/oas/latest.html": {
        "checks": {
            "status": 200,
            "200": "2023-06-16 02:48:12.856520"
        },
        "used": {
            "community-implementation-guide-standard": [
                "criteria/create-reusable-and-portable-code.md"
            ]
        }
    },
    "https://splasho.com/upgoer5/": {
        "checks": {
            "status": 200,
            "200": "2023-06-16 02:48:13.148935"
        },
        "used": {
            "community-implementation-guide-standard": [
                "criteria/use-plain-english.md"
            ]
        }
    },
    "https://standard.publiccode.net": {
        "checks": {
            "status": 200,
            "200": "2023-06-16 02:48:13.615039"
        },
        "used": {
            "publiccode.net": [
                "OSPO.md",
                "codebases/openzaak.html",
                "membership/index.md"
            ],
            "community-implementation-guide-standard": [
                "README.md"
            ]
        }
    },
    "https://translatewiki.net/": {
        "checks": {
            "status": 200,
            "200": "2023-06-16 02:48:17.209084"
        },
        "used": {
            "community-implementation-guide-standard": [
                "criteria/create-reusable-and-portable-code.md"
            ]
        }
    },
    "https://weblate.org/": {
        "checks": {
            "status": 200,
            "200": "2023-06-16 02:48:18.045003"
        },
        "used": {
            "community-implementation-guide-standard": [
                "criteria/create-reusable-and-portable-code.md"
            ]
        }
    },
    "https://welsh-revenue-authority.github.io/weeknotes/property-data-poc/": {
        "checks": {
            "status": 200,
            "200": "2023-06-16 02:48:18.789224"
        },
        "used": {
            "community-implementation-guide-standard": [
                "criteria/code-in-the-open.md"
            ]
        }
    },
    "https://www.bpmnquickguide.com/view-bpmn-quick-guide/": {
        "checks": {
            "status": 200,
            "200": "2023-06-16 02:48:20.055847"
        },
        "used": {
            "standard.publiccode.net": [
                "criteria/bundle-policy-and-source-code.md"
            ],
            "standard.publiccode.net-develop": [
                "criteria/bundle-policy-and-source-code.md"
            ],
            "community-implementation-guide-standard": [
                "criteria/bundle-policy-and-source-code.md"
            ]
        }
    },
    "https://www.discourse.org/": {
        "checks": {
            "status": 200,
            "200": "2023-06-16 02:48:26.322134"
        },
        "used": {
            "community-implementation-guide-standard": [
                "criteria/make-contributing-easy.md"
            ]
        }
    },
    "https://www.fixmystreet.com/": {
        "checks": {
            "status": 200,
            "200": "2023-06-16 02:48:26.715819"
        },
        "used": {
            "community-implementation-guide-standard": [
                "criteria/make-the-codebase-findable.md"
            ]
        }
    },
    "https://www.gnu.org/software/gettext/": {
        "checks": {
            "status": 200,
            "200": "2023-06-16 02:48:28.231587"
        },
        "used": {
            "community-implementation-guide-standard": [
                "criteria/create-reusable-and-portable-code.md"
            ]
        }
    },
    "https://www.gov.uk/service-manual/agile-delivery": {
        "checks": {
            "status": 200,
            "200": "2023-06-16 02:48:35.054223"
        },
        "used": {
            "standard.publiccode.net": [
                "criteria/document-codebase-maturity.md"
            ],
            "standard.publiccode.net-develop": [
                "criteria/document-codebase-maturity.md"
            ],
            "community-implementation-guide-standard": [
                "criteria/document-codebase-maturity.md"
            ]
        }
    },
    "https://www.masterportal.org/maintainer-group-en.html": {
        "checks": {
            "status": 200,
            "200": "2023-06-16 02:48:38.708348"
        },
        "used": {
            "community-implementation-guide-standard": [
                "criteria/welcome-contributors.md"
            ]
        }
    },
    "https://www.mkdocs.org/": {
        "checks": {
            "status": 200,
            "200": "2023-06-16 02:48:40.564944"
        },
        "used": {
            "community-implementation-guide-standard": [
                "criteria/document-the-code.md"
            ]
        }
    },
    "https://www.mumble.info/": {
        "checks": {
            "status": 200,
            "200": "2023-06-16 02:48:40.786047"
        },
        "used": {
            "community-implementation-guide-standard": [
                "criteria/make-contributing-easy.md"
            ]
        }
    },
    "https://www.notifications.service.gov.uk/features/roadmap": {
        "checks": {
            "status": 200,
            "200": "2023-06-16 02:48:41.502419"
        },
        "used": {
            "community-implementation-guide-standard": [
                "criteria/welcome-contributors.md"
            ]
        }
    },
    "https://www.transifex.com/": {
        "checks": {
            "status": 200,
            "200": "2023-06-16 02:48:42.731169"
        },
        "used": {
            "community-implementation-guide-standard": [
                "criteria/create-reusable-and-portable-code.md"
            ]
        }
    },
    "https://www.w3.org/International/techniques/authoring-html": {
        "checks": {
            "status": 200,
            "200": "2023-06-16 02:48:44.218535"
        },
        "used": {
            "community-implementation-guide-standard": [
                "criteria/create-reusable-and-portable-code.md"
            ]
        }
    },
    "https://www.w3.org/WAI/WCAG20/Understanding/reading-level.html": {
        "checks": {
            "status": 200,
            "200": "2023-06-16 02:48:44.384758"
        },
        "used": {
            "community-implementation-guide-standard": [
                "criteria/use-plain-english.md"
            ]
        }
    },
    "https://www.youtube.com/watch?v=KVleNqyohNY": {
        "checks": {
            "status": 200,
            "200": "2023-06-16 02:48:45.786286"
        },
        "used": {
            "community-implementation-guide-standard": [
                "criteria/publish-with-an-open-license.md"
            ]
        }
    },
    "https://zulip.com/": {
        "checks": {
            "status": 200,
            "200": "2023-06-16 02:48:48.896661"
        },
        "used": {
            "community-implementation-guide-standard": [
                "criteria/make-contributing-easy.md"
            ]
        }
    }
}
