{
    "urls": {
        "http://www.instagram.com/lottedale": {
            "checks": {
                "status": 429,
                "200": "2023-10-06 02:29:51.208232",
                "fail": {
                    "from": "2023-10-07 02:27:36.383901",
                    "from-code": 429,
                    "to": "2023-10-09 02:28:57.365495",
                    "to-code": 429
                }
            },
            "used": {
                "publiccode.net": [
                    "photos/jacco-brouwer-open-day-2019.jpg",
                    "who-we-are/team/ben-cerveny.jpg"
                ]
            }
        }
    },
    "repos": {
        "publiccode.net": "failing"
    }
}
